{
  "_class": "shapePath",
  "booleanOperation": -1,
  "clippingMaskMode": 0,
  "do_objectID": "9C1CA8E9-AD78-4514-8CD5-9B2FB19B01BE",
  "edited": true,
  "exportOptions": {
    "_class": "exportOptions",
    "exportFormats": [
    ],
    "includedLayerIds": [
    ],
    "layerOptions": 0,
    "shouldTrim": false
  },
  "frame": {
    "_class": "rect",
    "constrainProportions": false,
    "height": 4.284000000000006,
    "width": 4.22799999999998,
    "x": 194.5860000000001,
    "y": 4.143999999999991
  },
  "hasClippingMask": false,
  "isClosed": true,
  "isFixedToViewport": false,
  "isFlippedHorizontal": false,
  "isFlippedVertical": false,
  "isLocked": false,
  "isVisible": true,
  "layerListExpandedType": 0,
  "maintainScrollPosition": false,
  "name": "Path",
  "nameIsFixed": false,
  "pointRadiusBehaviour": 1,
  "points": [
    {
      "_class": "curvePoint",
      "cornerRadius": 0,
      "curveFrom": "{0.77814569536424016, 1}",
      "curveMode": 2,
      "curveTo": "{0.22185430463575984, 1}",
      "hasCurveFrom": true,
      "hasCurveTo": true,
      "point": "{0.49999999999999661, 1}"
    },
    {
      "_class": "curvePoint",
      "cornerRadius": 0,
      "curveFrom": "{1, 0.20915032679738552}",
      "curveMode": 2,
      "curveTo": "{1, 0.79411764705882271}",
      "hasCurveFrom": true,
      "hasCurveTo": true,
      "point": "{1, 0.49999999999999833}"
    },
    {
      "_class": "curvePoint",
      "cornerRadius": 0,
      "curveFrom": "{0.22185430463575984, 0}",
      "curveMode": 2,
      "curveTo": "{0.77814569536424016, 0}",
      "hasCurveFrom": true,
      "hasCurveTo": true,
      "point": "{0.49999999999999661, 0}"
    },
    {
      "_class": "curvePoint",
      "cornerRadius": 0,
      "curveFrom": "{0, 0.79411764705882271}",
      "curveMode": 2,
      "curveTo": "{0, 0.20915032679738552}",
      "hasCurveFrom": true,
      "hasCurveTo": true,
      "point": "{0, 0.49999999999999833}"
    }
  ],
  "resizingConstraint": 63,
  "resizingType": 0,
  "rotation": 0,
  "shouldBreakMaskChain": false,
  "style": {
    "_class": "style",
    "blur": {
      "_class": "blur",
      "center": "{0.5, 0.5}",
      "isEnabled": false,
      "motionAngle": 0,
      "radius": 10,
      "saturation": 1,
      "type": 0
    },
    "borderOptions": {
      "_class": "borderOptions",
      "dashPattern": [
      ],
      "isEnabled": true,
      "lineCapStyle": 0,
      "lineJoinStyle": 0
    },
    "borders": [
    ],
    "colorControls": {
      "_class": "colorControls",
      "brightness": 0,
      "contrast": 1,
      "hue": 0,
      "isEnabled": false,
      "saturation": 1
    },
    "contextSettings": {
      "_class": "graphicsContextSettings",
      "blendMode": 0,
      "opacity": 1
    },
    "do_objectID": "7A126C26-FBE1-4466-8DC8-49DBEC1AF793",
    "endMarkerType": 0,
    "fills": [
    ],
    "innerShadows": [
    ],
    "miterLimit": 10,
    "shadows": [
    ],
    "startMarkerType": 0,
    "windingRule": 1
  }
}